fedpredict/__init__.py
fedpredict/fedpredict.py
fedpredict/fedpredict_core.py
fedpredict/fedpredict_torch.py
fedpredict/utils/__init__.py
fedpredict/utils/utils.py
fedpredict/utils/compression_methods/__init__.py
fedpredict/utils/compression_methods/fedkd.py
fedpredict/utils/compression_methods/fedpsarsification.py
fedpredict/utils/compression_methods/parameters_svd.py
fedpredict/utils/compression_methods/quantization.py
fedpredict/utils/compression_methods/sparsification.py
fedpredict-0.0.67.dist-info/licenses/LICENSE
fedpredict-0.0.67.dist-info/METADATA
fedpredict-0.0.67.dist-info/WHEEL
fedpredict-0.0.67.dist-info/top_level.txt
fedpredict-0.0.67.dist-info/RECORD
