Metadata-Version: 2.4
Name: fedpredict
Version: 0.0.67
Summary: FedPredict is a personalization plugin for Federated Learning methods.
Author-email: "Cláudio G. S. Capanema" <claudiogs.capanema@gmail.com>
Maintainer-email: "Cláudio G. S. Capanema" <claudiogs.capanema@gmail.com>
Project-URL: homepage, https://github.com/claudiocapanema/fedpredict
Project-URL: documentation, https://claudiocapanema.github.io/fedpredict/
Classifier: Programming Language :: Python :: 3
Classifier: License :: OSI Approved :: BSD License
Classifier: Operating System :: OS Independent
Requires-Python: >=3.7
License-File: LICENSE
Requires-Dist: numpy>=1.20
Requires-Dist: scikit-learn>=1.6.0
Provides-Extra: torch
Requires-Dist: torch>=2.2.0; extra == "torch"
Provides-Extra: tf
Requires-Dist: tensorflow>=2.12; extra == "tf"
Provides-Extra: full
Requires-Dist: torch>=2.2.0; extra == "full"
Requires-Dist: tensorflow>=2.12; extra == "full"
Dynamic: license-file
